{"google":"","tagline":"Combinators and Function Decorators for JavaScript","note":"Don't delete this file! It's used internally to help with page regeneration.","name":"oscin.es","body":"[oscin-es] is a JavaScript library based on the standard logical combinators as well as a number of practical combinators and function decorators based on the book [JavaScript Allongé][ja].\r\n\r\n### Support or Contact\r\n[oscin-es] was written by Reg Braithwaite (@raganwald). It is published under the [MIT License].\r\n\r\n[oscin-es]: https://github.com/oscin-es/oscin-es.github.com\r\n[ja]: http://leanpub.com/javascript-allonge\r\n[MIT License]: http://opensource.org/licenses/MIT"}